proxydata_scrapy/__init__.py
proxydata_scrapy/middlewares.py
proxydata_scrapy-0.0.2b0.dist-info/LICENSE
proxydata_scrapy-0.0.2b0.dist-info/METADATA
proxydata_scrapy-0.0.2b0.dist-info/WHEEL
proxydata_scrapy-0.0.2b0.dist-info/top_level.txt
proxydata_scrapy-0.0.2b0.dist-info/RECORD
