Metadata-Version: 2.1
Name: proxydata-scrapy
Version: 0.0.2b0
Summary: Middleware for proxying scrapy requests through the service proxyfordevelopers.com
Home-page: UNKNOWN
Author: nekidaem
Author-email: order@nekidaem.ru
License: UNKNOWN
Platform: UNKNOWN
Classifier: Programming Language :: Python :: 3
Classifier: License :: OSI Approved :: MIT License
Classifier: Operating System :: OS Independent
Requires-Python: >=3.6
